idefix_cli/__init__.py
idefix_cli/__main__.py
idefix_cli/_backports.py
idefix_cli/_theme.py
idefix_cli/lib.py
idefix_cli/py.typed
idefix_cli/_commands/__init__.py
idefix_cli/_commands/clean.py
idefix_cli/_commands/clone.py
idefix_cli/_commands/conf.py
idefix_cli/_commands/digest.py
idefix_cli/_commands/read.py
idefix_cli/_commands/run.py
idefix_cli/_commands/switch.py
idefix_cli/_commands/write.py
idefix_cli-6.0.3.dist-info/entry_points.txt
idefix_cli-6.0.3.dist-info/licenses/LICENSE
idefix_cli-6.0.3.dist-info/WHEEL
idefix_cli-6.0.3.dist-info/METADATA
idefix_cli-6.0.3.dist-info/RECORD
