Metadata-Version: 2.4
Name: idefix_cli
Version: 6.0.3
Summary: A command line utility belt for Idefix
Author: C.M.T. Robert
Requires-Python: >=3.10
Classifier: Programming Language :: Python :: 3
Classifier: Typing :: Typed
License-File: LICENSE
Requires-Dist: exceptiongroup>=1.0.0 ; python_full_version < '3.11'
Requires-Dist: inifix>=5.1.0
Requires-Dist: packaging>=21.0
Requires-Dist: termcolor>=2.3.0
Requires-Dist: typing-extensions>=4.1.0;python_version < '3.11'
Project-URL: Homepage, https://github.com/neutrinoceros/idefix_cli
